Metadata-Version: 2.1
Name: wynker
Version: 1.0.0
Summary: WYNKER provides Starter Kits for Flask.
Home-page: UNKNOWN
Author: Abhijeet Sonawane
Author-email: abhijeet.sonawane001@gmail.com
License: MIT
Keywords: flaskspot wynker wynker-cli starterkit flask boilerplate
Platform: UNKNOWN
Classifier: License :: OSI Approved :: MIT License
Classifier: Programming Language :: Python :: 3
Classifier: Programming Language :: Python :: 3.6
Classifier: Programming Language :: Python :: 3.7
Classifier: Programming Language :: Python :: 3.8
Classifier: Programming Language :: Python :: 3.9
License-File: LICENSE
Requires-Dist: click (==7.1.2)
Requires-Dist: colorama
Requires-Dist: Jinja2
